funcstash/__init__.py
funcstash/package.py
funcstash-1.1.0.dist-info/licenses/LICENSE
funcstash-1.1.0.dist-info/METADATA
funcstash-1.1.0.dist-info/WHEEL
funcstash-1.1.0.dist-info/top_level.txt
funcstash-1.1.0.dist-info/RECORD
