Metadata-Version: 2.4
Name: funcstash
Version: 1.1.0
Summary: A package that adds useful functions to Python.
Home-page: https://github.com/DementiaGaming/py-plus-plus
Author: Dementia Gaming
Classifier: Programming Language :: Python :: 3
Classifier: License :: OSI Approved :: MIT License
License-File: LICENSE
Dynamic: author
Dynamic: classifier
Dynamic: description
Dynamic: description-content-type
Dynamic: home-page
Dynamic: license-file
Dynamic: summary
